CHANGES.md
LICENSE
MANIFEST.in
README.md
VERSION
setup.py
pyerse/__init__.py
pyerse/__main__.py
pyerse/ciclos.py
pyerse/comercializador.py
pyerse/periodos_horarios.py
pyerse/simulador.py
pyerse.egg-info/PKG-INFO
pyerse.egg-info/SOURCES.txt
pyerse.egg-info/dependency_links.txt
pyerse.egg-info/entry_points.txt
pyerse.egg-info/top_level.txt