Metadata-Version: 2.1
Name: pyerse
Version: 0.0.4
Summary: Provides algorithms and an API for Portugal Energy Regulator (ERSE)
Home-page: http://github.com/dgomes/pyerse
Author: Diogo Gomes
Author-email: diogogomes@gmail.com
License: MIT License
Platform: UNKNOWN
